kozmoai_finviz/__init__.py
kozmoai_finviz/models/__init__.py
kozmoai_finviz/models/compare_groups.py
kozmoai_finviz/models/equity_profile.py
kozmoai_finviz/models/equity_screener.py
kozmoai_finviz/models/key_metrics.py
kozmoai_finviz/models/price_performance.py
kozmoai_finviz/models/price_target.py
kozmoai_finviz/models/py.typed
kozmoai_finviz/py.typed
kozmoai_finviz/utils/__init__.py
kozmoai_finviz/utils/definitions.py
kozmoai_finviz/utils/presets/__init__.py
kozmoai_finviz/utils/presets/all_stocks.ini
kozmoai_finviz/utils/presets/analyst_strong_buy.ini
kozmoai_finviz/utils/presets/buffet_like.ini
kozmoai_finviz/utils/presets/bull_runs_over_10pct.ini
kozmoai_finviz/utils/presets/canslim.ini
kozmoai_finviz/utils/presets/cheap_dividend.ini
kozmoai_finviz/utils/presets/cheap_oversold.ini
kozmoai_finviz/utils/presets/continued_momentum.ini
kozmoai_finviz/utils/presets/death_cross.ini
kozmoai_finviz/utils/presets/fastgrowths.ini
kozmoai_finviz/utils/presets/golden_cross.ini
kozmoai_finviz/utils/presets/growth_stocks.ini
kozmoai_finviz/utils/presets/heavy_inst_ins.ini
kozmoai_finviz/utils/presets/large_cap_rsi20.ini
kozmoai_finviz/utils/presets/large_cap_rsi80.ini
kozmoai_finviz/utils/presets/modified_dreman.ini
kozmoai_finviz/utils/presets/modified_neff.ini
kozmoai_finviz/utils/presets/newhigh.ini
kozmoai_finviz/utils/presets/profitable_low_price_sales.ini
kozmoai_finviz/utils/presets/recent_growth_support.ini
kozmoai_finviz/utils/presets/screener_template.ini
kozmoai_finviz/utils/presets/short_squeeze.ini
kozmoai_finviz/utils/presets/undervalue.ini
kozmoai_finviz/utils/presets/weak_support_top_performers.ini
kozmoai_finviz/utils/py.typed
kozmoai_finviz/utils/screener_helper.py
kozmoai_finviz-1.3.0.dev202506081902.dist-info/METADATA
kozmoai_finviz-1.3.0.dev202506081902.dist-info/WHEEL
kozmoai_finviz-1.3.0.dev202506081902.dist-info/entry_points.txt
kozmoai_finviz-1.3.0.dev202506081902.dist-info/RECORD
